rectset/__init__.py
rectset/pseudopotential.py
rectset/rectangle_electrode.py
rectset-1.0.1.dist-info/LICENSE
rectset-1.0.1.dist-info/METADATA
rectset-1.0.1.dist-info/WHEEL
rectset-1.0.1.dist-info/top_level.txt
rectset-1.0.1.dist-info/RECORD
