Metadata-Version: 2.1
Name: rectset
Version: 1.0.1
Summary: Analytical potentials for rectangle electrodes in a surface ion trap
Author-email: Carmelo Mordini <carmelo.mordini@gmail.com>
License: MIT License
Project-URL: Homepage, https://github.com/carmelom/rectset
Keywords: python,trapped ions,surface electrodes,SET,ion trap,quantum computing
Classifier: Programming Language :: Python :: 3
Classifier: License :: OSI Approved :: MIT License
Classifier: Development Status :: 4 - Beta
Classifier: Operating System :: OS Independent
Classifier: Intended Audience :: Science/Research
Requires-Python: >=3.8
License-File: LICENSE
Requires-Dist: numpy
